tdns.py
tdns-0.2.0.dist-info/top_level.txt
tdns-0.2.0.dist-info/METADATA
tdns-0.2.0.dist-info/DESCRIPTION.rst
tdns-0.2.0.dist-info/metadata.json
tdns-0.2.0.dist-info/WHEEL
tdns-0.2.0.dist-info/RECORD
