Metadata-Version: 2.0
Name: tdns
Version: 0.2.0
Summary: An asynchronous Tornado wrapper for pycares
Home-page: http://github.com/gmr/tdns
Author: Gavin M. Roy
Author-email: gavinmroy@gmail.com
License: Copyright (c) 2016 Gavin M. Roy
Requires-Dist: pycares (>=1,<2)
Requires-Dist: tornado (>=4.0)
